fishtaindlib/__init__.py
fishtaindlib/bollinger/__init__.py
fishtaindlib/bollinger/bollingerbandwidth.py
fishtaindlib-0.1.dist-info/METADATA
fishtaindlib-0.1.dist-info/WHEEL
fishtaindlib-0.1.dist-info/top_level.txt
fishtaindlib-0.1.dist-info/RECORD
