Metadata-Version: 2.1
Name: fishtaindlib
Version: 0.1
Summary: A Python Library by Finnovesh for Technical Indicators commonly used for Trading in Financial markets
Home-page: UNKNOWN
Author: Finnovesh (Finnovesh Incorporation)
Author-email: <finnovesh@gmail.com>
License: UNKNOWN
Keywords: python,keygennerator,keygen,password
Platform: UNKNOWN
Classifier: Development Status :: 1 - Planning
Classifier: Intended Audience :: Developers
Classifier: Programming Language :: Python :: 3
Classifier: Operating System :: Unix
Classifier: Operating System :: MacOS :: MacOS X
Classifier: Operating System :: Microsoft :: Windows
Requires-Dist: backtrader
